{
  "salas": {
    "1": {
      "id": "01",
      "portas": {
        "1": {
          "identificador": "A",
          "corredor": "04"
        },
        "2": {
          "identificador": "B",
          "corredor": "01"
        }
      }
    },
    "2": {
      "id": "02",
      "portas": {
        "1": {
          "identificador": "A",
          "corredor": "01"
        },
        "2": {
          "identificador": "B",
          "corredor": "02"
        }
      }
    },
    "3": {
      "id": "03",
      "portas": {
        "1": {
          "identificador": "A",
          "corredor": "02"
        },
        "2": {
          "identificador": "B",
          "corredor": "05"
        }
      }
    },
    "4": {
      "id": "04",
      "portas": {
        "1": {
          "identificador": "B",
          "corredor": "03"
        }
      }
    },
    "5": {
      "id": "05",
      "portas": {
        "1": {
          "identificador": "A",
          "corredor": "06"
        },
        "2": {
          "identificador": "B",
          "corredor": "03"
        }
      }
    },
    "6": {
      "id": "06",
      "portas": {
        "1": {
          "identificador": "A",
          "corredor": "04"
        },
        "2": {
          "identificador": "B",
          "corredor": "07"
        }
      }
    },
    "7": {
      "id": "07",
      "portas": {
        "1": {
          "identificador": "A",
          "corredor": "09"
        },
        "2": {
          "identificador": "B",
          "corredor": "07"
        }
      }
    },
    "8": {
      "id": "08",
      "portas": {
        "1": {
          "identificador": "A",
          "corredor": "10"
        },
        "2": {
          "identificador": "B",
          "corredor": "05"
        }
      }
    },
    "9": {
      "id": "09",
      "portas": {
        "1": {
          "identificador": "A",
          "corredor": "08"
        }
      }
    },
    "10": {
      "id": "10",
      "portas": {
        "1": {
          "identificador": "A",
          "corredor": "08"
        },
        "2": {
          "identificador": "B",
          "corredor": "11"
        },
        "3": {
          "identificador": "C",
          "corredor": "06"
        }
      }
    },
    "11": {
      "id": "11",
      "portas": {
        "1": {
          "identificador": "A",
          "corredor": "12"
        },
        "2": {
          "identificador": "B",
          "corredor": "15"
        }
      }
    },
    "12": {
      "id": "12",
      "portas": {
        "1": {
          "identificador": "A",
          "corredor": "12"
        },
        "2": {
          "identificador": "B",
          "corredor": "09"
        },
        "3": {
          "identificador": "C",
          "corredor": "13"
        }
      }
    },
    "13": {
      "id": "13",
      "portas": {
        "1": {
          "identificador": "A",
          "corredor": "13"
        },
        "2": {
          "identificador": "B",
          "corredor": "10"
        }
      }
    },
    "14": {
      "id": "14",
      "portas": {
        "1": {
          "identificador": "A",
          "corredor": "14"
        },
        "2": {
          "identificador": "B",
          "corredor": "16"
        }
      }
    },
    "15": {
      "id": "15",
      "portas": {
        "1": {
          "identificador": "A",
          "corredor": "14"
        },
        "2": {
          "identificador": "B",
          "corredor": "11"
        },
        "3": {
          "identificador": "C",
          "corredor": "17"
        }
      }
    },
  "16": {
      "id": "16",
      "portas": {
        "1": {
          "identificador": "A",
          "corredor": "15"
        },
        "2": {
          "identificador": "B",
          "corredor": "18"
        }
      }
    },
  "17": {
      "id": "17",
      "portas": {
        "1": {
          "identificador": "A",
          "corredor": "18"
        },
        "2": {
          "identificador": "B",
          "corredor": "19"
        }
      }
    },
  "18": {
      "id": "18",
      "portas": {
        "1": {
          "identificador": "A",
          "corredor": "20"
        },
        "2": {
          "identificador": "B",
          "corredor": "19"
        }
      }
    },
  "19": {
      "id": "19",
      "portas": {
        "1": {
          "identificador": "A",
          "corredor": "16"
        },
        "2": {
          "identificador": "B",
          "corredor": "20"
        }
      }
    },
  "20": {
      "id": "20",
      "portas": {
        "1": {
          "identificador": "A",
          "corredor": "17"
        }
      }
    }
  },
  "corredores": {
	"1": {
      "id": "01",
      "portas": {
        "1": {
          "identificador": "A",
          "sala": "01"
        },
        "2": {
          "identificador": "B",
          "sala": "02"
        }
      }
    },
	"2": {
      "id": "02",
      "portas": {
        "1": {
          "identificador": "A",
          "sala": "02"
        },
        "2": {
          "identificador": "B",
          "sala": "03"
        }
      }
    },
	"3": {
      "id": "03",
      "portas": {
        "1": {
          "identificador": "A",
          "sala": "04"
        },
        "2": {
          "identificador": "B",
          "sala": "05"
        }
      }
    },
	"4": {
      "id": "04",
      "portas": {
        "1": {
          "identificador": "A",
          "sala": "01"
        },
        "2": {
          "identificador": "C",
          "sala": "06"
        }
      }
    },
	"5": {
      "id": "05",
      "portas": {
        "1": {
          "identificador": "A",
          "sala": "03"
        },
        "2": {
          "identificador": "C",
          "sala": "08"
        }
      }
    },
	"6": {
      "id": "06",
      "portas": {
        "1": {
          "identificador": "A",
          "sala": "05"
        },
        "2": {
          "identificador": "C",
          "sala": "10"
        }
      }
    },
	"7": {
      "id": "07",
      "portas": {
        "1": {
          "identificador": "A",
          "sala": "06"
        },
        "2": {
          "identificador": "B",
          "sala": "07"
        }
      }
    },
	"8": {
      "id": "08",
      "portas": {
        "1": {
          "identificador": "A",
          "sala": "09"
        },
        "2": {
          "identificador": "B",
          "sala": "10"
        }
      }
    },
	"9": {
      "id": "09",
      "portas": {
        "1": {
          "identificador": "A",
          "sala": "07"
        },
        "2": {
          "identificador": "B",
          "sala": "12"
        }
      }
    },
	"10": {
      "id": "10",
      "portas": {
        "1": {
          "identificador": "A",
          "sala": "08"
        },
        "2": {
          "identificador": "B",
          "sala": "13"
        }
      }
    },
	"11": {
      "id": "11",
      "portas": {
        "1": {
          "identificador": "A",
          "sala": "10"
        },
        "2": {
          "identificador": "B",
          "sala": "15"
        }
      }
    },
	"12": {
      "id": "12",
      "portas": {
        "1": {
          "identificador": "A",
          "sala": "11"
        },
        "2": {
          "identificador": "B",
          "sala": "12"
        }
      }
    },
	"13": {
      "id": "13",
      "portas": {
        "1": {
          "identificador": "A",
          "sala": "12"
        },
        "2": {
          "identificador": "B",
          "sala": "13"
        }
      }
    },
	"14": {
      "id": "14",
      "portas": {
        "1": {
          "identificador": "A",
          "sala": "14"
        },
        "2": {
          "identificador": "B",
          "sala": "15"
        }
      }
    },
	"15": {
      "id": "15",
      "portas": {
        "1": {
          "identificador": "A",
          "sala": "11"
        },
        "2": {
          "identificador": "B",
          "sala": "16"
        }
      }
    },
	"16": {
      "id": "16",
      "portas": {
        "1": {
          "identificador": "A",
          "sala": "14"
        },
        "2": {
          "identificador": "B",
          "sala": "19"
        }
      }
    },
	"17": {
      "id": "17",
      "portas": {
        "1": {
          "identificador": "A",
          "sala": "15"
        },
        "2": {
          "identificador": "B",
          "sala": "20"
        }
      }
    },
	"18": {
      "id": "18",
      "portas": {
        "1": {
          "identificador": "A",
          "sala": "16"
        },
        "2": {
          "identificador": "B",
          "sala": "17"
        }
      }
    },
	"19": {
      "id": "19",
      "portas": {
        "1": {
          "identificador": "A",
          "sala": "17"
        },
        "2": {
          "identificador": "B",
          "sala": "18"
        }
      }
    },
	"20": {
      "id": "20",
      "portas": {
        "1": {
          "identificador": "A",
          "sala": "18"
        },
        "2": {
          "identificador": "C",
          "sala": "19"
        }
      }
    }
  }
}
